dapple_planner-0.9.2.dist-info/METADATA
dapple_planner-0.9.2.dist-info/WHEEL
HPGO.cpython-37m-darwin.so
dapple_planner-0.9.2.dist-info/RECORD
