Metadata-Version: 2.1
Name: dapple_planner
Version: 0.9.2
Requires-Dist: graphviz~=0.13
Summary: Hybrid Parallelism Global Orchestration
Author: Yi Rong <i@rongyi.io>
Author-Email: Yi Rong <i@rongyi.io>
License: Apache-2.0
